CHANGES.txt
LICENSE
MANIFEST.in
README.rst
requirements.txt
setup.py
scipion_chem_toxcsm.egg-info/PKG-INFO
scipion_chem_toxcsm.egg-info/SOURCES.txt
scipion_chem_toxcsm.egg-info/dependency_links.txt
scipion_chem_toxcsm.egg-info/entry_points.txt
scipion_chem_toxcsm.egg-info/requires.txt
scipion_chem_toxcsm.egg-info/top_level.txt
toxCSM/__init__.py
toxCSM/bibtex.py
toxCSM/constants.py
toxCSM/objects.py
toxCSM/protocols/__init__.py
toxCSM/protocols/protocol_toxCSM.py
toxCSM/tests/__init__.py
toxCSM/tests/testViewer.py
toxCSM/viewers/__init__.py
toxCSM/viewers/viewers_toxCSM.py
toxCSM/wizards/__init__.py
toxCSM/wizards/wizard_toxcsm.py