Metadata-Version: 2.1
Name: scipion-chem-toxcsm
Version: 0.2
Summary: Scipion framework plugin for the use of toxCSM software tool
Home-page: https://github.com/scipion-chem/scipion-chem-toxCSM
Author: Veronica Gamo
Author-email: veronica.gamoparejo@usp.ceu.es
Keywords: scipion toxCSM scipion-3.0 cheminformatics
License-File: LICENSE
Requires-Dist: beautifulsoup4
Requires-Dist: scipion-pyworkflow
Requires-Dist: scipion-em
Requires-Dist: scipion-chem
